{
    "name": "Piaggio P.180 Avanti",
    "icao": "P180",
    "engines": {
        "number": 2,
        "type": "T"
    },
    "weightClass": "S",
    "category": {
        "srs": 2,
        "lahso": 1,
        "recat": "F"
    },
    "ceiling": 41000,
    "rate": {
        "climb":      3000,
        "descent":    1500,
        "accelerate": 5,
        "decelerate": 3
    },
    "runway": {
        "takeoff": 0.900,
        "landing": 0.900
    },
    "speed":{
        "min":     105,
        "landing": 120,
        "cruise":  300,
        "cruiseM": 0.65,
        "max":     320,
        "maxM":    null
    },
    "capability": {
        "ils": true,
        "fix": true
    }
}
