{
    "radio": {
        "twr": "Helsinki Tower",
        "app": "Helsinki Radar",
        "dep": "Helsinki Radar"
    },
    "icao": "EFHK",
    "iata": "HEL",
    "magnetic_north": 8.4,
    "ctr_radius": 60,
    "ctr_ceiling": 28500,
    "initial_alt": 4000,
    "position": ["N60d19m02", "E24d57m48", "180ft"],
    "rr_radius_nm": 5,
    "rr_center": ["N60d19m02", "E24d57m48"],
    "has_terrain": false,
    "wind": {
        "angle": 240,
        "speed": 8
    },
    "arrivalRunway": "22L",
    "departureRunway": "22R",
    "airspace": [
        {
            "floor": 0,
            "ceiling": 285,
            "airspace_class": "C",
            "poly": [
                ["N60d49m13", "E24d46m56"],
                ["N60d54m13", "E24d47m04"],
                ["N60d54m53", "E25d32m36"],
                ["N60d44m52", "E25d58m18"],
                ["N60d08m59", "E26d43m38"],
                ["N60d08m00", "E26d33m00"],
                ["N59d53m00", "E25d52m00"],
                ["N59d54m30", "E25d20m00"],
                ["N59d53m27", "E24d59m49"],
                ["N59d53m00", "E24d51m00"],
                ["N59d42m00", "E23d59m31"],
                ["N59d40m01", "E23d50m27"],
                ["N59d54m19", "E23d39m09"],
                ["N60d28m56", "E23d53m10"],
                ["N60d36m06", "E24d03m48"],
                ["N60d36m00", "E24d16m14"],
                ["N60d44m33", "E24d29m08"],
                ["N60d49m13", "E24d46m56"]
            ]
        }
    ],
    "fixes": {
        "ABSUT": ["N60d13m08.61", "E24d44m03.74"],
        "ADBIX": ["N60d32m13.67", "E24d59m12.90"],
        "ADIVO": ["N60d17m51.00", "E23d58m53.00"],
        "ARVEP": ["N60d14m58.00", "E26d23m57.00"],
        "ASTIV": ["N60d14m05.00", "E24d25m26.00"],
        "BALTI": ["N59d54m15.00", "E25d15m06.00"],
        "BIMVU": ["N60d27m36.54", "E25d15m58.56"],
        "DEVKA": ["N60d09m01.00", "E24d46m01.00"],
        "DIVAM": ["N59d50m54.00", "E23d35m37.00"],
        "DOBAN": ["N59d47m58.00", "E24d27m09.00"],
        "ELKUN": ["N60d27m23.11", "E24d50m04.30"],
        "ELPEN": ["N60d18m50.00", "E25d29m45.00"],
        "ENUTO": ["N60d28m53.00", "E24d46m32.00"],
        "ERSAV": ["N60d18m30.00", "E24d34m42.00"],
        "EXEVO": ["N60d15m10.22", "E24d48m29.31"],
        "GEDLO": ["N60d10m15.28", "E24d37m46.68"],
        "GIRLA": ["N60d11m27.00", "E24d33m43.00"],
        "GOVMI": ["N60d08m47.00", "E25d20m58.00"],
        "GUMVO": ["N60d23m38.10", "E25d07m08.03"],
        "HK416": ["N60d23m52.55", "E25d07m40.07"],
        "HK418": ["N60d11m54.92", "E24d59m57.32"],
        "HK419": ["N60d19m47.43", "E25d10m55.00"],
        "HK427": ["N60d21m44.76", "E24d36m49.48"],
        "HK428": ["N60d16m05.52", "E24d46m21.17"],
        "HK451": ["N60d18m16.80", "E24d46m54.99"],
        "HK461": ["N60d19m05.74", "E24d46m25.05"],
        "HK711": ["N60d16m19.79", "E25d05m53.91"],
        "HK766": ["N60d15m53.05", "E25d04m54.92"],
        "HK801": ["N60d10m19.01", "E24d35m45.88"],
        "HK802": ["N60d13m59.34", "E24d28m59.21"],
        "HK803": ["N60d05m14.38", "E24d24m48.13"],
        "HK804": ["N60d06m06.13", "E24d43m29.98"],
        "HK806": ["N59d58m49.93", "E25d19m00.76"],
        "HK807": ["N60d25m04.20", "E25d25m13.30"],
        "HK811": ["N60d08m13.32", "E24d33m22.43"],
        "HK813": ["N60d05m08.86", "E24d26m44.41"],
        "HK814": ["N60d04m32.54", "E24d40m06.94"],
        "HK817": ["N60d21m18.87", "E25d07m37.09"],
        "HK821": ["N60d30m02.93", "E24d47m18.66"],
        "HK822": ["N60d32m18.26", "E24d56m19.98"],
        "HK823": ["N60d29m00.05", "E24d33m21.53"],
        "HK844": ["N60d09m05.85", "E25d19m59.81"],
        "HK846": ["N60d04m36.34", "E25d02m09.32"],
        "HK849": ["N60d18m22.65", "E24d35m33.61"],
        "HK851": ["N60d12m40.65", "E24d23m12.59"],
        "HK852": ["N60d08m17.70", "E24d31m23.33"],
        "HK856": ["N60d14m55.80", "E24d45m48.21"],
        "HK859": ["N60d17m08.95", "E25d00m36.11"],
        "HK860": ["N60d14m39.61", "E24d47m22.35"],
        "HK861": ["N60d06m51.40", "E25d11m03.96"],
        "HK862": ["N60d21m23.87", "E24d44m56.59"],
        "HK863": ["N60d19m52.61", "E25d09m05.02"],
        "HK864": ["N60d17m49.22", "E24d54m17.87"],
        "HK866": ["N60d21m14.14", "E25d01m49.34"],
        "HK871": ["N60d26m02.64", "E24d30m13.81"],
        "HK873": ["N60d15m04.40", "E24d18m42.97"],
        "HK874": ["N60d12m28.95", "E24d10m09.16"],
        "HK881": ["N60d25m44.97", "E25d26m51.58"],
        "HK883": ["N60d29m59.29", "E25d19m06.04"],
        "HK886": ["N60d29m36.92", "E24d34m00.61"],
        "HK887": ["N60d33m34.24", "E25d12m30.34"],
        "HK888": ["N60d35m18.64", "E25d08m27.32"],
        "HK889": ["N60d42m46.80", "E25d16m48.67"],
        "HK890": ["N60d35m53.50", "E25d17m15.10"],
        "HK891": ["N60d18m53.92", "E25d11m34.98"],
        "HK892": ["N60d34m35.11", "E25d31m38.51"],
        "HK893": ["N60d35m17.34", "E25d31m01.19"],
        "HK894": ["N60d08m35.87", "E24d48m55.85"],
        "HK896": ["N60d25m32.74", "E24d51m15.25"],
        "HK897": ["N60d24m48.12", "E24d52m35.91"],
        "HK899": ["N60d12m24.52", "E24d25m34.18"],
        "HK900": ["N60d13m52.08", "E25d03m57.07"],
        "HK901": ["N60d04m16.70", "E25d02m18.99"],
        "HK902": ["N60d41m31.66", "E25d16m53.49"],
        "HK903": ["N60d24m22.06", "E24d56m47.14"],
        "HK904": ["N60d29m37.07", "E25d20m28.09"],
        "HK906": ["N60d25m55.07", "E25d27m14.27"],
        "HK907": ["N60d33m37.33", "E25d13m06.06"],
        "IDEPI": ["N60d42m39.00", "E25d47m39.00"],
        "IDMOP": ["N60d24m03.00", "E25d03m09.00"],
        "INTOR": ["N59d49m40.00", "E25d11m12.00"],
        "KUDOP": ["N59d58m46.00", "E24d04m36.00"],
        "KUVEM": ["N60d11m26.00", "E23d56m14.00"],
        "LAKUT": ["N60d26m17.00", "E23d52m35.00"],
        "LAVTU": ["N60d12m19.00", "E25d13m54.00"],
        "LULAB": ["N60d30m21.00", "E25d07m54.00"],
        "LUSEP": ["N60d57m08.00", "E25d15m53.00"],
        "LUVEX": ["N60d21m54.76", "E25d18m17.01"],
        "MAMOP": ["N60d34m30.00", "E25d59m04.00"],
        "MAROM": ["N60d26m52.00", "E24d02m37.00"],
        "NAPUN": ["N60d49m41.00", "E25d16m22.00"],
        "NEMVI": ["N60d16m01.45", "E24d33m23.97"],
        "NEPEK": ["N60d44m33.00", "E24d29m08.00"],
        "NIDAG": ["N60d11m51.00", "E24d50m50.00"],
        "NODMO": ["N60d32m31.00", "E25d02m06.64"],
        "NUNTO": ["N60d05m01.00", "E23d53m37.00"],
        "NUTRU": ["N60d17m24.00", "E25d27m17.00"],
        "OBONU": ["N60d09m31.66", "E25d08m21.74"],
        "OBUPU": ["N60d24m47.89", "E24d52m44.68"],
        "PENAD": ["N60d16m42.00", "E25d29m36.00"],
        "PEXEN": ["N59d54m47.00", "E23d49m28.00"],
        "PODOM": ["N60d12m20.89", "E24d40m10.57"],
        "REDBO": ["N60d25m38.00", "E24d51m52.00"],
        "RENKU": ["N59d53m09.00", "E24d53m48.10"],
        "RILBO": ["N60d11m37.00", "E24d16m43.00"],
        "RIPVI": ["N60d16m24.00", "E24d35m07.00"],
        "ROLAT": ["N60d17m57.00", "E25d31m20.00"],
        "ROPAM": ["N60d07m59.00", "E25d36m06.00"],
        "_RW04L": ["N60d18m46.61", "E24d54m13.93"],
        "_RW04R": ["N60d18m40.65", "E24d56m10.94"],
        "_RW15": ["N60d19m48.99", "E24d57m52.19"],
        "_RW22L": ["N60d19m50.49", "E24d58m44.73"],
        "_RW22R": ["N60d19m52.11", "E24d56m38.01"],
        "_RW33": ["N60d18m25.44", "E24d59m17.83"],
        "SUTAX": ["N60d29m38.26", "E24d59m05.08"],
        "TEDMU": ["N60d27m46.64", "E25d14m09.63"],
        "TEVRU": ["N60d49m16.00", "E24d49m29.00"],
        "UNURU": ["N60d27m53.00", "E24d45m56.00"],
        "UREDA": ["N60d14m20.00", "E24d37m23.00"],
        "VAGIP": ["N60d18m35.00", "E24d25m20.00"],
        "VAMRA": ["N60d13m33.00", "E24d33m27.00"],
        "VAVIS": ["N60d14m06.00", "E24d50m39.00"],
        "VEPIN": ["N60d37m53.00", "E26d19m59.00"],
        "VETUD": ["N60d30m30.00", "E24d48m41.00"],
        "VIBEP": ["N60d27m33.00", "E24d14m39.00"],
        "XELBU": ["N60d23m36.37", "E25d04m53.30"],
        "XOMRI": ["N60d26m34.00", "E25d13m38.00"],
        "BAMEB": ["N60d09m41.94", "E25d08m31.04"],
        "DIPMO": ["N60d12m06.79", "E24d41m48.99"],
        "EMPEV": ["N60d14m17.68", "E24d44m25.00"],
        "LAVDI": ["N60d14m14.15", "E24d46m26.73"],
        "TIXED": ["N60d25m44.59", "E25d11m49.01"],
        "HAGIS": ["N60d12m31", "E24d54m00"],
        "HAKKI": ["N60d16m43", "E25d05m30"],
        "KOLIS": ["N60d27m04", "E25d01m07"],
        "LILJA": ["N60d19m26", "E25d12m31"],
        "LINTU": ["N60d22m47", "E24d41m04"],
        "OGELI": ["N60d13m51", "E24d59m16"],

        "NIPIB": ["N59d40m57", "E23d00m48"],
        "ODESO": ["N60d19m34", "E22d39m02"],
        "PEKUX": ["N60d24m19", "E22d37m32"],
        "IPMOT": ["N60d27m11", "E23d10m35"],
        "AMROT": ["N60d29m38", "E23d42m33"],
        "ERNUT": ["N61d17m10", "E25d16m47"],
        "OTPAL": ["N61d16m08", "E25d40m32"],
        "ROKVI": ["N60d51m39", "E27d01m23"],
        "ARLOM": ["N60d47m25", "E27d43m53"],
        "LEDUN": ["N59d58m30", "E26d06m42"],
        "ARSAM": ["N59d26m51", "E25d21m25"],
        "BEKNA": ["N59d31m40", "E24d56m05"],
        "GEPTA": ["N59d34m48", "E25d29m14"],
        "SORPA": ["N59d37m01", "E24d50m49"],

        "PEPIG": ["N60d08m29", "E22d35m59"],
        "RATMU": ["N60d14m16", "E26d32m09"],
        "INLOG": ["N60d10m18", "E26d56m47"],
        "OLEMA": ["N60d14m00", "E27d28m30"],
        "RATLA": ["N60d51m30", "E28d20m18"],
        "MUSTI": ["N59d45m07", "E24d22m47"],
        "TLL": ["N59d24m41", "E24d50m18"],
        "TUSBI": ["N61d04m05", "E26d18m23"],
        "UMUGI": ["N60d02m14", "E22d41m41"],
        "NISVI": ["N61d07m34", "E24d02m55"],
        "ABSER": ["N59d53m50", "E22d59m48"],
        "PISOX": ["N59d46m41", "E22d45m04"],
        "DIPUM": ["N61d13m00", "E24d55m08"],
        "TN471": ["N59d34m15.4", "E25d02m47.4"],
        "TN903": ["N59d37m11.0", "E24d26m19.1"],
        "TN425": ["N59d48m10.3", "E24d53m11.0"],

        "_22RDME25": ["N60.3089654", "E24.8951079"]
    },
    "runways":[
        {
            "name": ["04L", "22R"],
            "name_offset": [[0.9, 1], [0, 0]],
            "end": [["N60d18m46.61", "E24d54m13.93", "133.6ft"], ["N60d19m53.42", "E24d56m40.90", "179.9ft"]],
            "ils": [true, true]
        },
        {
            "name": ["04R", "22L"],
            "name_offset": [[0.9, 1], [-0.8, -1]],
            "end": [["N60d18m40.65", "E24d56m10.94", "153.2ft"], ["N60d19m50.49", "E24d58m44.73", "148.6ft"]],
            "ils": [true, true]
        },
        {
            "name": ["15", "33"],
            "name_offset": [[0, 0], [-0.7, 1]],
            "end": [["N60d19m48.99", "E24d57m52.19", "162.9ft"], ["N60d18m25.44", "E24d59m17.83", "147.1ft"]],
            "ils": [true, true]
        }
    ],
    "sids": {
        "ASTIV": {
            "icao": "ASTIV",
            "name": "ASTIV",
            "suffix": {"22R":"3N"},
            "rwy": {
                 "22R": ["_22RDME25", "HK451", ["ASTIV", "S250-"]]
            },
            "exitPoints": {
                "MUSTI": ["DOBAN", "MUSTI"],
                "TLL": ["DOBAN", "TLL"],
                "TN471": ["DOBAN", "TN471"],
                "TN903": ["DOBAN", "TN903"],
                "TN425": ["RENKU", "TN425"]
            },
            "draw": [["_22RDME25", "HK451", "ASTIV"],
                     ["ASTIV", "DOBAN", "MUSTI*"],
                     ["DOBAN", "TLL*"],
                     ["DOBAN", "TN471*"],
                     ["DOBAN", "TN903*"],
                     ["ASTIV", "RENKU", "TN425*"]]
        },
        "DEVKA": {
            "icao": "DEVKA",
            "name": "DEVKA",
            "suffix": {"22L":"1F"},
            "rwy": {
                 "22L": [["VAVIS", "S230-"], ["DEVKA", "S230-"]]
            },
            "exitPoints": {
                "MUSTI": ["DOBAN", "MUSTI"],
                "TLL": ["DOBAN", "TLL"],
                "TN471": ["DOBAN", "TN471"],
                "TN903": ["DOBAN", "TN903"],
                "TN425": ["RENKU", "TN425"]
            },
            "draw": [["VAVIS", "DEVKA"],
                     ["DEVKA", "DOBAN", "MUSTI*"],
                     ["DOBAN", "TLL*"],
                     ["DOBAN", "TN471*"],
                     ["DOBAN", "TN903*"],
                     ["DEVKA", "RENKU", "TN425*"]]
        },
        "ELPEN": {
            "icao": "ELPEN",
            "name": "ELPEN",
            "suffix": {"04R":"4C"},
            "rwy": {
                 "04R": ["HK416", ["ELPEN", "S250-"]]
            },
            "exitPoints": {
                "ARLOM": ["ARVEP", "RATMU", "ARLOM"],
                "INLOG": ["ARVEP", "RATMU", "INLOG"],
                "OLEMA": ["ARVEP", "RATMU", "OLEMA"],
                "RATLA": ["ARVEP", "RATMU", "RATLA"],
                "MUSTI": ["DOBAN", "MUSTI"],
                "TLL": ["DOBAN", "TLL"],
                "TN471": ["DOBAN", "TN471"],
                "TN903": ["DOBAN", "TN903"],
                "TN425": ["RENKU", "TN425"]
            },
            "draw": [["HK416", "ELPEN"],
                     ["ELPEN", "ARVEP", "RATMU", "ARLOM*"],
                     ["RATMU", "INLOG*"],
                     ["RATMU", "OLEMA*"],
                     ["RATMU", "RATLA*"],
                     ["ELPEN", "DOBAN", "MUSTI*"],
                     ["DOBAN", "TLL*"],
                     ["DOBAN", "TN471*"],
                     ["DOBAN", "TN903*"],
                     ["ELPEN", "RENKU", "TN425*"]]
        },
        "ENUTO": {
            "icao": "ENUTO",
            "name": "ENUTO",
            "suffix": {"22R":"3N"},
            "rwy": {
                 "22R": ["_22RDME25", "HK461", ["HK427", "S250-"], "ENUTO"]
            },
            "exitPoints": {
                "ARLOM": ["ARVEP", "RATMU", "ARLOM"],
                "INLOG": ["ARVEP", "RATMU", "INLOG"],
                "OLEMA": ["ARVEP", "RATMU", "OLEMA"],
                "RATLA": ["ARVEP", "RATMU", "RATLA"],
                "TUSBI": ["IDEPI", "TUSBI"],
                "NISVI": ["NEPEK", "NISVI"],
                "DIPUM": ["TEVRU", "DIPUM"]
            },
            "draw": [["_22RDME25", "HK461", "HK427", "ENUTO"],
                     ["ENUTO", "ARVEP", "RATMU", "ARLOM*"],
                     ["RATMU", "INLOG*"],
                     ["RATMU", "OLEMA*"],
                     ["RATMU", "RATLA*"],
                     ["ENUTO", "IDEPI", "TUSBI*"],
                     ["ENUTO", "NEPEK", "NISVI*"],
                     ["ENUTO", "TEVRU", "DIPUM*"]]
        },
        "ERSAV": {
            "icao": "ERSAV",
            "name": "ERSAV",
            "suffix": {"33":"3P"},
            "rwy": {
                 "33": [["ERSAV", "S250-"]]
            },
            "exitPoints": {
                "PEPIG": ["ADIVO", "PEPIG"],
                "UMUGI": ["KUVEM", "UMUGI"],
                "ABSER": ["NUNTO", "ABSER"],
                "PISOX": ["NUNTO", "PISOX"]
            },
            "draw": [["ERSAV"],
                     ["ERSAV", "ADIVO", "PEPIG*"],
                     ["ERSAV", "KUVEM", "UMUGI*"],
                     ["ERSAV", "NUNTO", "ABSER*"],
                     ["NUNTO", "PISOX*"]]
        },
        "GIRLA": {
            "icao": "GIRLA",
            "name": "GIRLA",
            "suffix": {"15":"3D"},
            "rwy": {
                 "15": [["RIPVI", "S250-"], "GIRLA"]
            },
            "exitPoints": {
                "MUSTI": ["DOBAN", "MUSTI"],
                "TLL": ["DOBAN", "TLL"],
                "TN471": ["DOBAN", "TN471"],
                "TN903": ["DOBAN", "TN903"],
                "TN425": ["RENKU", "TN425"]
            },
            "draw": [["RIPVI", "GIRLA"],
                     ["GIRLA", "DOBAN", "MUSTI*"],
                     ["DOBAN", "TLL*"],
                     ["DOBAN", "TN471*"],
                     ["DOBAN", "TN903*"],
                     ["GIRLA", "RENKU", "TN425*"]]
        },
        "GOVMI": {
            "icao": "GOVMI",
            "name": "GOVMI",
            "suffix": {"15":"2D"},
            "rwy": {
                 "15": [["LAVTU", "S250-"], "GOVMI"]
            },
            "draw": [["LAVTU", "GOVMI"]]
        },
        "IDMOP": {
            "icao": "IDMOP",
            "name": "IDMOP",
            "suffix": {"33":"3P"},
            "rwy": {
                 "33": [["IDMOP", "S250-"]]
            },
            "exitPoints": {
                "ARLOM": ["ARVEP", "RATMU", "ARLOM"],
                "INLOG": ["ARVEP", "RATMU", "INLOG"],
                "OLEMA": ["ARVEP", "RATMU", "OLEMA"],
                "RATLA": ["ARVEP", "RATMU", "RATLA"],
                "TUSBI": ["IDEPI", "TUSBI"]
            },
            "draw": [["IDMOP"],
                     ["IDMOP", "ARVEP", "RATMU", "ARLOM*"],
                     ["RATMU", "INLOG*"],
                     ["RATMU", "OLEMA*"],
                     ["RATMU", "RATLA*"],
                     ["IDMOP", "IDEPI", "TUSBI*"]]
        },
        "LULAB": {
            "icao": "LULAB",
            "name": "LULAB",
            "suffix": {"04R":"2C"},
            "rwy": {
                 "04R": ["HK416", ["LULAB", "S250-"]]
            },
            "exitPoints": {
                "NISVI": ["NEPEK", "NISVI"],
                "DIPUM": ["TEVRU", "DIPUM"]
            },
            "draw": [["HK416", "LULAB"],
                     ["LULAB", "NEPEK", "NISVI*"],
                     ["LULAB", "TEVRU", "DIPUM*"]]
        },
        "NIDAG": {
            "icao": "NIDAG",
            "name": "NIDAG",
            "suffix": {"15":"2U"},
            "rwy": {
                 "15": [["NIDAG", "S250-"]]
            },
            "exitPoints": {
                "MUSTI": ["DOBAN", "MUSTI"],
                "TLL": ["DOBAN", "TLL"],
                "TN471": ["DOBAN", "TN471"],
                "TN903": ["DOBAN", "TN903"],
                "TN425": ["RENKU", "TN425"]
            },
            "draw": [["NIDAG"],
                     ["NIDAG", "DOBAN", "MUSTI*"],
                     ["DOBAN", "TLL*"],
                     ["DOBAN", "TN471*"],
                     ["DOBAN", "TN903*"],
                     ["NIDAG", "RENKU", "TN425*"]]
        },
        "NUTRU": {
            "icao": "NUTRU",
            "name": "NUTRU",
            "suffix": {"15":"3D"},
            "rwy": {
                 "15": [["NUTRU", "S250-"]]
            },
            "exitPoints": {
                "ARLOM": ["ARVEP", "RATMU", "ARLOM"],
                "INLOG": ["ARVEP", "RATMU", "INLOG"],
                "OLEMA": ["ARVEP", "RATMU", "OLEMA"],
                "RATLA": ["ARVEP", "RATMU", "RATLA"],
                "TUSBI": ["IDEPI", "TUSBI"]
            },
            "draw": [["NUTRU"],
                     ["NUTRU", "ARVEP", "RATMU", "ARLOM*"],
                     ["RATMU", "INLOG*"],
                     ["RATMU", "OLEMA*"],
                     ["RATMU", "RATLA*"],
                     ["NUTRU", "IDEPI", "TUSBI*"]]
        },
        "PENAD": {
            "icao": "PENAD",
            "name": "PENAD",
            "suffix": {"22L":"5F"},
            "rwy": {
                 "22L": [["VAVIS", "S230-"], ["HK418", "A25+|S230-"], "PENAD"]
            },
            "exitPoints": {
                "ARLOM": ["ARVEP", "RATMU", "ARLOM"],
                "INLOG": ["ARVEP", "RATMU", "INLOG"],
                "OLEMA": ["ARVEP", "RATMU", "OLEMA"],
                "RATLA": ["ARVEP", "RATMU", "RATLA"],
                "TUSBI": ["IDEPI", "TUSBI"]
            },
            "draw": [["VAVIS", "HK418", "PENAD"],
                     ["PENAD", "ARVEP", "RATMU", "ARLOM*"],
                     ["RATMU", "INLOG*"],
                     ["RATMU", "OLEMA*"],
                     ["RATMU", "RATLA*"],
                     ["PENAD", "IDEPI", "TUSBI*"]]
        },
        "REDBO": {
            "icao": "REDBO",
            "name": "REDBO",
            "suffix": {"33":"3P"},
            "rwy": {
                 "33": [["REDBO", "S250-"]]
            },
            "exitPoints": {
                "NISVI": ["NEPEK", "NISVI"],
                "DIPUM": ["TEVRU", "DIPUM"]
            },
            "draw": [["REDBO"],
                     ["REDBO", "NEPEK", "NISVI*"],
                     ["REDBO", "TEVRU", "DIPUM*"]]
        },
        "RILBO": {
            "icao": "RILBO",
            "name": "RILBO",
            "suffix": {"22R":"1N"},
            "rwy": {
                 "22R": ["_22RDME25", "HK451", ["ASTIV", "S250-"], "RILBO"]
            },
            "exitPoints": {
                "ABSER": ["NUNTO", "ABSER"],
                "PISOX": ["NUNTO", "PISOX"]
            },
            "draw": [["_22RDME25", "HK451", "ASTIV", "RILBO"],
                     ["RILBO", "NUNTO", "ABSER*"],
                     ["NUNTO", "PISOX*"]]
        },
        "RIPVI": {
            "icao": "RIPVI",
            "name": "RIPVI",
            "suffix": {"15":"3D"},
            "rwy": {
                 "15": [["RIPVI", "S250-"]]
            },
            "exitPoints": {
                "PEPIG": ["ADIVO", "PEPIG"],
                "UMUGI": ["KUVEM", "UMUGI"],
                "NISVI": ["NEPEK", "NISVI"],
                "ABSER": ["NUNTO", "ABSER"],
                "PISOX": ["NUNTO", "PISOX"],
                "DIPUM": ["TEVRU", "DIPUM"]
            },
            "draw": [["RIPVI"],
                     ["RIPVI", "ADIVO", "PEPIG*"],
                     ["RIPVI", "KUVEM", "UMUGI*"],
                     ["RIPVI", "NEPEK", "NISVI*"],
                     ["RIPVI", "NUNTO", "ABSER*"],
                     ["NUNTO", "PISOX*"],
                     ["RIPVI", "TEVRU", "DIPUM*"]]
        },
        "ROLAT": {
            "icao": "ROLAT",
            "name": "ROLAT",
            "suffix": {"04R":"3S"},
            "rwy": {
                 "04R": ["HK419", ["ROLAT", "S250-"]]
            },
            "exitPoints": {
                "ARLOM": ["ARVEP", "RATMU", "ARLOM"],
                "INLOG": ["ARVEP", "RATMU", "INLOG"],
                "OLEMA": ["ARVEP", "RATMU", "OLEMA"],
                "RATLA": ["ARVEP", "RATMU", "RATLA"],
                "MUSTI": ["DOBAN", "MUSTI"],
                "TLL": ["DOBAN", "TLL"],
                "TN471": ["DOBAN", "TN471"],
                "TN903": ["DOBAN", "TN903"],
                "TUSBI": ["IDEPI", "TUSBI"],
                "TN425": ["RENKU", "TN425"]
            },
            "draw": [["HK419", "ROLAT"],
                     ["ROLAT", "ARVEP", "RATMU", "ARLOM*"],
                     ["RATMU", "INLOG*"],
                     ["RATMU", "OLEMA*"],
                     ["RATMU", "RATLA*"],
                     ["ROLAT", "DOBAN", "MUSTI*"],
                     ["DOBAN", "TLL*"],
                     ["DOBAN", "TN471*"],
                     ["DOBAN", "TN903*"],
                     ["ROLAT", "IDEPI", "TUSBI*"],
                     ["ROLAT", "RENKU", "TN425*"]]
        },
        "UNURU": {
            "icao": "UNURU",
            "name": "UNURU",
            "suffix": {"04L":"4Z"},
            "rwy": {
                 "04L": ["HK903", ["UNURU", "S250-"]]
            },
            "exitPoints": {
                "PEPIG": ["ADIVO", "PEPIG"],
                "UMUGI": ["KUVEM", "UMUGI"],
                "NISVI": ["NEPEK", "NISVI"],
                "ABSER": ["NUNTO", "ABSER"],
                "PISOX": ["NUNTO", "PISOX"],
                "DIPUM": ["TEVRU", "DIPUM"]
            },
            "draw": [["HK903", "UNURU"],
                     ["UNURU", "ADIVO", "PEPIG*"],
                     ["UNURU", "KUVEM", "UMUGI*"],
                     ["UNURU", "NEPEK", "NISVI*"],
                     ["UNURU", "NUNTO", "ABSER*"],
                     ["NUNTO", "PISOX*"],
                     ["UNURU", "TEVRU", "DIPUM*"]]
        },
        "UREDA": {
            "icao": "UREDA",
            "name": "UREDA",
            "suffix": {"22R":"3N"},
            "rwy": {
                 "22R": ["_22RDME25", "HK428", ["UREDA", "S250-"]]
            },
            "exitPoints": {
                "MUSTI": ["DOBAN", "MUSTI"],
                "TLL": ["DOBAN", "TLL"],
                "TN471": ["DOBAN", "TN471"],
                "TN903": ["DOBAN", "TN903"],
                "TN425": ["RENKU", "TN425"]
            },
            "draw": [["_22RDME25", "HK428", "UREDA"],
                     ["UREDA", "DOBAN", "MUSTI*"],
                     ["DOBAN", "TLL*"],
                     ["DOBAN", "TN471*"],
                     ["DOBAN", "TN903*"],
                     ["UREDA", "RENKU", "TN425*"]]
        },
        "VAGIP": {
            "icao": "VAGIP",
            "name": "VAGIP",
            "suffix": {"22R":"1N"},
            "rwy": {
                 "22R": ["_22RDME25", "HK461", ["VAGIP", "S250-"]]
            },
            "exitPoints": {
                "PEPIG": ["ADIVO", "PEPIG"],
                "UMUGI": ["KUVEM", "UMUGI"]
            },
            "draw": [["_22RDME25", "HK461", "VAGIP"],
                     ["VAGIP", "ADIVO", "PEPIG*"],
                     ["VAGIP", "KUVEM", "UMUGI*"]]
        },
        "VAMRA": {
            "icao": "VAMRA",
            "name": "VAMRA",
            "suffix": {"33":"1P"},
            "rwy": {
                 "33": [["ERSAV", "S250-"], "VAMRA"]
            },
            "exitPoints": {
                "MUSTI": ["DOBAN", "MUSTI"],
                "TLL": ["DOBAN", "TLL"],
                "TN471": ["DOBAN", "TN471"],
                "TN903": ["DOBAN", "TN903"],
                "TN425": ["RENKU", "TN425"]
            },
            "draw": [["ERSAV", "VAMRA"],
                     ["VAMRA", "DOBAN", "MUSTI*"],
                     ["DOBAN", "TLL*"],
                     ["DOBAN", "TN471*"],
                     ["DOBAN", "TN903*"],
                     ["VAMRA", "RENKU", "TN425*"]]
        },
        "VETUD": {
            "icao": "VETUD",
            "name": "VETUD",
            "suffix": {"04R":"3C"},
            "rwy": {
                 "04R": ["HK416", ["LULAB", "S250-"], "VETUD"]
            },
            "exitPoints": {
                "PEPIG": ["ADIVO", "PEPIG"],
                "UMUGI": ["KUVEM", "UMUGI"],
                "ABSER": ["NUNTO", "ABSER"],
                "PISOX": ["NUNTO", "PISOX"]
            },
            "draw": [["HK416", "LULAB", "VETUD"],
                     ["VETUD", "ADIVO", "PEPIG*"],
                     ["VETUD", "KUVEM", "UMUGI*"],
                     ["VETUD", "NUNTO", "ABSER*"],
                     ["NUNTO", "PISOX*"]]
        },
        "XOMRI": {
            "icao": "XOMRI",
            "name": "XOMRI",
            "suffix": {"04R":"1C"},
            "rwy": {
                 "04R": ["HK416", ["XOMRI", "S250-"]]
            },
            "exitPoints": {
                "TUSBI": ["IDEPI", "TUSBI"]
            },
            "draw": [["HK416", "XOMRI"],
                     ["XOMRI", "IDEPI", "TUSBI*"]]
        }
    },

    "stars": {
        "DIVAM": {
            "icao": "DIVAM",
            "name": "DIVAM",
            "suffix": {"04L":"1B", "04R":"1R", "15":"1M", "22L":"2A", "22R":"2V", "33":"1W"},
            "entryPoints": {
                "NIPIB": ["NIPIB"]
            },
            "body": [["DIVAM", "A100+"], ["PEXEN", "A70+|S250-"]],
            "rwy": {
                "04L": [["HK803", "A35+|S220-"], "HK801", ["PODOM", "A23+|S210-"]],
                "04R": [["HK813", "A35+|S220-"], "HK811", ["GEDLO", "A33+|S210-"]],
                "15" : [["HK804", "A35+"], "HK766", ["HK817", "A30+"], ["SUTAX", "A20+|S220-"], ["HK822", "A20+|S220-"], "HK821", ["ELKUN", "A20+|S210-"]],
                "22L": [["HK804", "A35+"], "HK891", ["LUVEX", "A30+|S220-"], ["HK906", "A30+|S220-"], "HK904", ["BIMVU", "A30+|S210-"]],
                "22R": [["HK804", "A35+"], ["HK881", "A30+|S220-"], "HK883", ["TEDMU", "A20|S210-"]],
                "33" : [["HK846", "A35+|S220-"], "HK861", ["OBONU", "A30+|S210-"]]
            },
            "draw": []
        },
        "INTOR": {
            "icao": "INTOR",
            "name": "INTOR",
            "suffix": {"04L":"4B", "04R":"4R", "15":"5M", "22L":"3A", "22R":"3V", "33":"4W"},
            "entryPoints": {
                "ARSAM": ["ARSAM"],
                "BEKNA": ["BEKNA"],
                "GEPTA": ["GEPTA"],
                "SORPA": ["SORPA"]
            },
            "body": [["INTOR", "A120+"], ["BALTI", "S250-"], "HK806"],
            "rwy": {
                "04L": [["HK804", "A30+|S220-"], "HK801", ["PODOM", "A23+|S210-"]],
                "04R": ["HK901", ["HK894", "A33+|S220-"], ["HK814", "A33+|S220-"], "HK811", ["GEDLO", "A33+|S210-"]],
                "15" : [["HK817", "A30+"], ["SUTAX", "A20+|S220-"], ["HK822", "A20+|S220-"], "HK821", ["ELKUN", "A20+|S210-"]],
                "22L": ["HK891", ["LUVEX", "A30+|S220-"], ["HK906", "A30+|S220-"], "HK904", ["BIMVU", "A30+|S210-"]],
                "22R": [["HK881", "A30+|S220-"], "HK883", ["TEDMU", "A20|S210-"]],
                "33" : ["HK861", ["OBONU", "A30+|S210-"]]
            },
            "draw": []
        },
        "LAKUT": {
            "icao": "LAKUT",
            "name": "LAKUT",
            "suffix": {"04L":"5B", "04R":"5R", "15":"5M", "22L":"3A", "22R":"3V", "33":"5W"},
            "entryPoints": {
                "AMROT": ["AMROT"],
                "IPMOT": ["IPMOT"],
                "ODESO": ["ODESO"],
                "PEKUX": ["PEKUX"]
            },
            "body": [["LAKUT", "A100+"], ["MAROM", "A70+|S250-"]],
            "rwy": {
                "04L": ["VIBEP", ["HK802", "A30+|S220-"], "HK801", ["PODOM", "A23+|S210-"]],
                "04R": ["VIBEP", ["HK899", "A33+|S220-"], "HK811", ["GEDLO", "A33+|S210-"]],
                "15" : [["HK823", "A30+|S220-"], ["HK822", "A20+|S220-"], "HK821", ["ELKUN", "A20+|S210-"]],
                "22L": ["HK886", ["NODMO", "A30+|S220-"], ["HK907", "A30|S220-"], "HK904", ["BIMVU", "A30+|S210-"]],
                "22R": [["HK886", "A30+"], ["ADBIX", "A20+|S220-"], ["HK887", "A20|S220-"], "HK883", ["TEDMU", "A20|S210-"]],
                "33" : ["VIBEP", "HK862", ["HK846", "A35+|S220-"], "HK861", ["OBONU", "A30+|S210-"]]
            },
            "draw": []
        },
        "LUSEP": {
            "icao": "LUSEP",
            "name": "LUSEP",
            "suffix": {"04L":"1B", "04R":"1R", "15":"1M", "22L":"2A", "22R":"3V", "33":"1W"},
            "entryPoints": {
                "ERNUT": ["ERNUT"],
                "OTPAL": ["OTPAL"]
            },
            "body": [["LUSEP", "A100+"], ["NAPUN", "A70+|S250-"]],
            "rwy": {
                "04L": ["HK890", ["NEMVI", "A30+|S220-"], ["HK802", "A30+|S220-"], "HK801", ["PODOM", "A23+|S210-"]],
                "04R": ["HK890", "HK897", ["HK899", "A33+|S220-"], "HK811", ["GEDLO", "A33+|S210-"]],
                "15" : ["HK889", ["HK888", "A30+"], ["HK822", "A20+|S220-"], "HK821", ["ELKUN", "A20+|S210-"]],
                "22L": [["HK902", "A30+|S220-"], ["HK907", "A30|S220-"], "HK904", ["BIMVU", "A30+|S210-"]],
                "22R": [["HK902", "A30+|S220-"], ["HK887", "A20|S220-"], "HK883", ["TEDMU", "A20|S210-"]],
                "33" : ["HK863", ["HK844", "A30+|S220-"], "HK861", ["OBONU", "A30+|S210-"]]
            },
            "draw": []
        },
        "MAROM": {
            "icao": "MAROM",
            "name": "MAROM",
            "suffix": {"04L":"4B"},
            "body": [["MAROM", "A70+|S250-"], ["HK871", "A30+"], "HK849", ["HK851", "A23|S220-"], ["HK852", "A23"], ["PODOM", "A23|S210-"]],
            "draw": []
        },
        "NAPUN": {
            "icao": "NAPUN",
            "name": "NAPUN",
            "suffix": {"04L":"1B"},
            "body": [["NAPUN", "A70+|S250-"], "HK890", ["HK896", "A30+"], "HK849", ["HK851", "A23|S220-"], ["HK852", "A23"], ["PODOM", "A23|S210-"]],
            "draw": []
        },
        "PEXEN": {
            "icao": "PEXEN",
            "name": "PEXEN",
            "suffix": {"04L":"4B", "22R":"3V"},
            "entryPoints": {
                "PEXEN": [["PEXEN", "A70+|S250-"]]
            },
            "body": ["KUDOP"],
            "rwy": {
                "04L": [["HK874", "A30+|S220-"], ["HK873", "A30+"], ["HK851", "A23|S220-"], ["HK852", "A23"], ["PODOM", "A23|S210-"]],
                "22R": [["HK886", "A30+"], ["ADBIX", "A20+|S220-"], ["HK887", "A20|S220-"], "HK883", ["TEDMU", "A20|S210-"]]
            },
            "draw": []
        },
        "ROPAM": {
            "icao": "ROPAM",
            "name": "ROPAM",
            "suffix": {"04L":"1B", "04R":"1R", "15":"1M", "22L":"2A", "22R":"2V", "33":"1W"},
            "entryPoints": {
                "LEDUN": ["LEDUN"]
            },
            "body": [["ROPAM", "S250-"]],
            "rwy": {
                "04L": ["HK711", ["HK804", "A30+|S220-"], "HK801", ["PODOM", "A23+|S210-"]],
                "04R": ["HK711", ["HK894", "A33+|S220-"], ["HK814", "A33+|S220-"], "HK811", ["GEDLO", "A33+|S210-"]],
                "15" : [["HK817", "A30+"], ["SUTAX", "A20+|S220-"], ["HK822", "A20+|S220-"], "HK821", ["ELKUN", "A20+|S210-"]],
                "22L": [["HK906", "A30+|S220-"], "HK904", ["BIMVU", "A30+|S210-"]],
                "22R": [["HK881", "A30+|S220-"], "HK883", ["TEDMU", "A20|S210-"]],
                "33" : [["HK844", "A30+|S220-"], "HK861", ["OBONU", "A30+|S210-"]]
            },
            "draw": []
        },
        "VEPIN": {
            "icao": "VEPIN",
            "name": "VEPIN",
            "suffix": {"04L":"1B", "04R":"1R", "15":"1M", "22L":"2A", "22R":"2V", "33":"1W"},
            "entryPoints": {
                "ARLOM": ["ARLOM"],
                "ROKVI": ["ROKVI"]
            },
            "body": [["VEPIN", "A100+"], ["MAMOP", "A70+|S250-"]],
            "rwy": {
                "04L": ["HK807", "HK711", ["HK804", "A30+|S220-"], "HK801", ["PODOM", "A23+|S210-"]],
                "04R": ["HK807", "HK711", ["HK894", "A33+|S220-"], ["HK814", "A33+|S220-"], "HK811", ["GEDLO", "A33+|S210-"]],
                "15" : [["HK888", "A30+"], ["HK822", "A20+|S220-"], "HK821", ["ELKUN", "A20+|S210-"]],
                "22L": [["HK892", "A30+|S220-"], "HK904", ["BIMVU", "A30+|S210-"]],
                "22R": [["HK893", "A30+|S220-"], "HK883", ["TEDMU", "A20|S210-"]],
                "33" : [["HK844", "A30+|S220-"], "HK861", ["OBONU", "A30+|S210-"]]
            },
            "draw": []
        }
    },

    "spawnPatterns": [
        {
            "destination": "",
            "origin": "EFHK",
            "category": "departure",
            "method": "random",
            "route": "EFHK.RILBO.PISOX",
            "rate": 2,
            "altitude": null,
            "speed": null,
            "airlines":    [
                ["fin", 90],
                ["nax", 30],
                ["sas", 12],
                ["dlh", 8],
                ["klm", 3],
                ["ber", 3],

                ["baw", 2],
                ["vkg", 2],
                ["tui", 2],
                ["tom", 2],
                ["tra", 1],
                ["ibe", 1],
                ["tap", 1]
            ]
        },
        {
            "destination": "",
            "origin": "EFHK",
            "category": "departure",
            "method": "random",
            "route": "EFHK.RILBO.ABSER",
            "rate": 2,
            "altitude": null,
            "speed": null,
            "airlines":    [
                ["fin", 90],
                ["nax", 30],
                ["sas", 12],
                ["dlh", 8],
                ["klm", 3],
                ["ber", 3],

                ["baw", 2],
                ["vkg", 2],
                ["tui", 2],
                ["tom", 2],
                ["tra", 1],
                ["ibe", 1],
                ["tap", 1]
            ]
        },
        {
            "destination": "",
            "origin": "EFHK",
            "category": "departure",
            "method": "random",
            "route": "EFHK.VAGIP.UMUGI",
            "rate": 1,
            "altitude": null,
            "speed": null,
            "airlines":    [
                ["fin", 90],
                ["nax", 30],
                ["sas", 12],
                ["dlh", 8],
                ["klm", 3],
                ["ber", 3],

                ["baw", 2],
                ["vkg", 2],
                ["tui", 2],
                ["tom", 2],
                ["tra", 1],
                ["ibe", 1],
                ["tap", 1]
            ]
        },
        {
            "destination": "",
            "origin": "EFHK",
            "category": "departure",
            "method": "random",
            "route": "EFHK.VAGIP.PEPIG",
            "rate": 1,
            "altitude": null,
            "speed": null,
            "airlines":    [
                ["fin", 90],
                ["nax", 30],
                ["sas", 12],
                ["dlh", 2],
                ["klm", 3],
                ["ber", 2],

                ["baw", 2],
                ["vkg", 2],
                ["tui", 2],
                ["tom", 2],
                ["tra", 1],
                ["ibe", 1],
                ["tap", 1]
            ]
        },
        {
            "destination": "",
            "origin": "EFHK",
            "category": "departure",
            "method": "random",
            "route": "EFHK.UREDA.MUSTI",
            "rate": 8,
            "altitude": null,
            "speed": null,
            "airlines":    [
                ["fin", 90],
                ["nax", 30],
                ["sas", 4],
                ["dlh", 8],
                ["klm", 3],
                ["ber", 3],
                ["thy", 3],
                ["bti", 3],

                ["baw", 2],
                ["vkg", 2],
                ["tui", 2],
                ["tom", 2],
                ["csa", 1],
                ["aui", 1],
                ["tra", 1],
                ["ibe", 1],
                ["tap", 1],
                ["qtr", 1]
            ]
        },
        {
            "destination": "",
            "origin": "EFHK",
            "category": "departure",
            "method": "random",
            "route": "EFHK.UREDA.TLL",
            "rate": 2,
            "altitude": null,
            "speed": null,
            "airlines":    [
                ["fin", 90],
                ["nax", 30],
                ["sas", 4],
                ["dlh", 8],
                ["klm", 3],
                ["ber", 3],
                ["thy", 3],
                ["bti", 3],

                ["baw", 2],
                ["vkg", 2],
                ["tui", 2],
                ["tom", 2],
                ["csa", 1],
                ["aui", 1],
                ["tra", 1],
                ["ibe", 1],
                ["tap", 1],
                ["qtr", 1]
            ]
        },
        {
            "destination": "",
            "origin": "EFHK",
            "category": "departure",
            "method": "random",
            "route": "EFHK.ENUTO.NISVI",
            "rate": 3,
            "altitude": null,
            "speed": null,
            "airlines":    [
                ["fin/long", 4],
                ["fin", 65],
                ["nax", 12],
                ["sas", 1]
            ]
        },
        {
            "destination": "",
            "origin": "EFHK",
            "category": "departure",
            "method": "random",
            "route": "EFHK.ENUTO.DIPUM",
            "rate": 3,
            "altitude": null,
            "speed": null,
            "airlines": [
                ["fin", 65],
                ["nax", 5]
            ]
        },
        {
            "destination": "",
            "origin": "EFHK",
            "category": "departure",
            "method": "random",
            "route": "EFHK.ENUTO.TUSBI",
            "rate": 3,
            "altitude": null,
            "speed": null,
            "airlines": [
                ["fin/long", 20],
                ["fin", 10],
                ["jal/long", 1],
                ["vkg", 1],
                ["tom", 1],
                ["tui", 1]
            ]
        },
        {
            "destination": "",
            "origin": "EFHK",
            "category": "departure",
            "method": "random",
            "route": "EFHK.ENUTO.ARLOM",
            "rate": 1,
            "altitude": null,
            "speed": null,
            "airlines": [
                ["fin/long", 20],
                ["fin", 10],
                ["jal/long", 1],
                ["vkg", 1],
                ["tom", 1],
                ["tui", 1]
            ]
        },
        {
            "destination": "",
            "origin": "EFHK",
            "category": "departure",
            "method": "random",
            "route": "EFHK.ENUTO.INLOG",
            "rate": 1,
            "altitude": null,
            "speed": null,
            "airlines": [
                ["fin/long", 20],
                ["fin", 10],
                ["jal/long", 1],
                ["vkg", 1],
                ["tom", 1],
                ["tui", 1]
            ]
        },
        {
            "destination": "",
            "origin": "EFHK",
            "category": "departure",
            "method": "random",
            "route": "EFHK.ENUTO.OLEMA",
            "rate": 1,
            "altitude": null,
            "speed": null,
            "airlines": [
                ["fin/long", 20],
                ["fin", 10],
                ["jal/long", 1],
                ["vkg", 1],
                ["tom", 1],
                ["tui", 1]
            ]
        },
        {
            "destination": "",
            "origin": "EFHK",
            "category": "departure",
            "method": "random",
            "route": "EFHK.ENUTO.RATLA",
            "rate": 1,
            "altitude": null,
            "speed": null,
            "airlines": [
                ["fin/long", 20],
                ["fin", 10],
                ["jal/long", 1],
                ["vkg", 1],
                ["tom", 1],
                ["tui", 1]
            ]
        },
        {
            "destination": "",
            "origin": "EFHK",
            "category": "departure",
            "method": "random",
            "route": "EFHK.UREDA.TN425",
            "rate": 1,
            "altitude": null,
            "speed": null,
            "airlines": [
                ["fin", 2]
            ]
        },

        {
            "destination": "EFHK",
            "origin": "",
            "category": "arrival",
            "method": "random",
            "route": "NIPIB.DIVAM.EFHK",
            "rate": 5,
            "altitude": 18000,
            "speed": 280,
            "airlines": [
                ["fin", 90],
                ["nax", 30],
                ["sas", 12],
                ["dlh", 8],
                ["klm", 3],
                ["ber", 3],
                ["bti", 1],

                ["baw", 2],
                ["vkg", 2],
                ["tui", 2],
                ["tom", 2],
                ["csa", 1],
                ["aui", 1],
                ["tra", 1],
                ["ibe", 1],
                ["tap", 1]
            ]
        },
        {
            "destination": "EFHK",
            "origin": "",
            "category": "arrival",
            "method": "random",
            "route": "ERNUT.LUSEP.EFHK",
            "rate": 2,
            "altitude": 14000,
            "speed": 280,
            "airlines": [
                ["fin", 65],
                ["nax", 5]
            ]
        },
        {
            "destination": "EFHK",
            "origin": "",
            "category": "arrival",
            "method": "random",
            "route": "OTPAL.LUSEP.EFHK",
            "rate": 2,
            "altitude": 18000,
            "speed": 280,
            "airlines": [
                ["fin", 65],
                ["nax", 5],
                ["fin/long", 5]
            ]
        },
        {
            "destination": "EFHK",
            "origin": "",
            "category": "arrival",
            "method": "random",
            "route": "ROKVI.VEPIN.EFHK",
            "rate": 3,
            "altitude": 15000,
            "speed": 280,
            "airlines": [
                ["fin/long", 20],
                ["jal/long", 1],
                ["fin", 10],
                ["afl", 1],
                ["vkg", 1],
                ["tom", 1],
                ["tui", 1]
            ]
        },
        {
            "destination": "EFHK",
            "origin": "",
            "category": "arrival",
            "method": "random",
            "route": "PEKUX.LAKUT.EFHK",
            "rate": 1,
            "altitude": 28000,
            "speed": 280,
            "airlines": [
                ["fin", 90],
                ["nax", 30],
                ["sas", 12],
                ["dlh", 8],
                ["klm", 3],
                ["ber", 3],

                ["baw", 2],
                ["vkg", 2],
                ["tui", 2],
                ["tom", 2],
                ["aui", 1],
                ["tra", 1],
                ["ibe", 1],
                ["tap", 1],

                ["fin/long", 2]
            ]
        },
        {
            "destination": "EFHK",
            "origin": "",
            "category": "arrival",
            "method": "random",
            "route": "IPMOT.LAKUT.EFHK",
            "rate": 1,
            "altitude": 16000,
            "speed": 280,
            "airlines": [
                ["fin", 90],
                ["nax", 30],
                ["sas", 12],

                ["baw", 2],
                ["vkg", 2],
                ["tui", 2],
                ["tom", 2],

                ["fin/long", 2]
            ]
        },
        {
            "destination": "EFHK",
            "origin": "",
            "category": "arrival",
            "method": "random",
            "route": "AMROT.LAKUT.EFHK",
            "rate": 2,
            "altitude": 12000,
            "speed": 280,
            "airlines": [
                ["fin", 90],
                ["nax", 30],
                ["sas", 12],

                ["baw", 1],
                ["vkg", 2],
                ["tui", 2],
                ["tom", 2],

                ["fin/long", 20]
            ]
        },
        {
            "destination": "EFHK",
            "origin": "",
            "category": "arrival",
            "method": "random",
            "route": "ODESO.LAKUT.EFHK",
            "rate": 4,
            "altitude": 22000,
            "speed": 280,
            "airlines": [
                ["fin", 90],
                ["nax", 30],
                ["sas", 12],
                ["dlh", 1],
                ["klm", 2],
                ["ber", 1],

                ["baw", 2],
                ["vkg", 2],
                ["tui", 2],
                ["tom", 2],
                ["tra", 1],
                ["ibe", 1],
                ["tap", 1],

                ["fin/long", 2]
            ]
        },
        {
            "destination": "EFHK",
            "origin": "",
            "category": "arrival",
            "method": "random",
            "route": "ARSAM.INTOR.EFHK",
            "rate": 1,
            "altitude": 25000,
            "speed": 280,
            "airlines": [
                ["fin", 90],
                ["nax", 30],
                ["sas", 1],
                ["dlh", 8],
                ["ber", 3],
                ["thy", 3],
                ["bti", 3],

                ["vkg", 2],
                ["tui", 2],
                ["tom", 2],
                ["csa", 1],
                ["aui", 1],
                ["ibe", 1],
                ["tap", 1],
                ["qtr", 1],

                ["fin/long", 2]
            ]
        },
        {
            "destination": "EFHK",
            "origin": "",
            "category": "arrival",
            "method": "random",
            "route": "SORPA.INTOR.EFHK",
            "rate": 2,
            "altitude": 15000,
            "speed": 280,
            "airlines": [
                ["fin", 90],
                ["nax", 30],
                ["sas", 6],
                ["dlh", 8],
                ["klm", 3],
                ["ber", 3],
                ["thy", 1],
                ["bti", 3],

                ["baw", 2],
                ["vkg", 2],
                ["tui", 2],
                ["tom", 2],
                ["csa", 1],
                ["aui", 1],
                ["tra", 1],
                ["ibe", 1],
                ["tap", 1],

                ["fin/long", 5]
            ]
        },
        {
            "destination": "EFHK",
            "origin": "",
            "category": "arrival",
            "method": "random",
            "route": "GEPTA.INTOR.EFHK",
            "rate": 1,
            "altitude": 19000,
            "speed": 280,
            "airlines": [
                ["fin", 90],
                ["nax", 30],
                ["dlh", 2],
                ["ber", 2],
                ["thy", 3],
                ["bti", 3],

                ["vkg", 2],
                ["tui", 2],
                ["tom", 2],
                ["csa", 1],
                ["aui", 1],
                ["qtr", 1],

                ["fin/long", 8]
            ]
        },
        {
            "destination": "EFHK",
            "origin": "",
            "category": "arrival",
            "method": "random",
            "route": "BEKNA.INTOR.EFHK",
            "rate": 2,
            "altitude": 22000,
            "speed": 280,
            "airlines": [
                ["fin", 90],
                ["nax", 30],
                ["sas", 4],
                ["dlh", 8],
                ["klm", 3],
                ["ber", 3],
                ["thy", 3],
                ["bti", 3],

                ["baw", 2],
                ["vkg", 2],
                ["tui", 2],
                ["tom", 2],
                ["csa", 1],
                ["aui", 1],
                ["tra", 1],
                ["ibe", 1],
                ["tap", 1],
                ["qtr", 1]
            ]
        },
        {
            "destination": "EFHK",
            "origin": "",
            "category": "arrival",
            "method": "random",
            "route": "LEDUN.ROPAM.EFHK",
            "rate": 2,
            "altitude": 10000,
            "speed": 250,
            "airlines": [
                ["fin/long", 20],
                ["jal/long", 1],
                ["fin", 10],
                ["qtr", 1],
                ["thy", 1],
                ["afl", 1],
                ["vkg", 1],
                ["tom", 1],
                ["tui", 1]
            ]
        }
    ]
}
