{
    "airac": 2213,
    "radio": {
        "twr": "Savannah Tower",
        "app": "Savannah Approach",
        "dep": "Savannah Departure"
    },
    "icao": "KSAV",
    "iata": "SAV",
    "magnetic_north": -5.5,
    "ctr_radius": 50,
    "ctr_ceiling": 10000,
    "initial_alt": 3000,
    "position": ["N32d07m39.298", "W81d12m07.675", "10ft"],
    "rangeRings": {
        "enabled": true,
        "center": ["N32d07m39.298", "W81d12m07.675"],
        "radius_nm": 5.0
    },
    "has_terrain": false,
    "wind": {
        "angle": 100,
        "speed": 3
    },
    "arrivalRunway": "10",
    "departureRunway": "10",
    "defaultMaps": ["Base Map"],
    "airspace": [
        {
            "floor": 0,
            "ceiling": 100,
            "airspace_class": "C",
            "poly": [
                ["N31d27m32.536", "W80d47m54.451"],
                ["N31d36m54.489", "W80d40m59.545"],
                ["N31d59m60.000", "W80d28m59.533"],
                ["N32d09m26.793", "W80d38m00.780"],
                ["N32d16m56.773", "W80d40m05.225"],
                ["N32d16m40.446", "W80d49m00.393"],
                ["N32d19m56.757", "W80d55m59.531"],
                ["N32d29m53.114", "W81d01m33.275"],
                ["N32d38m00.659", "W81d01m23.921"],
                ["N32d38m00.473", "W81d27m44.239"],
                ["N32d32m00.423", "W81d33m13.793"],
                ["N32d33m16.359", "W81d41m07.370"],
                ["N32d33m49.489", "W81d43m04.226"],
                ["N32d33m49.487", "W81d45m28.993"],
                ["N32d32m39.052", "W81d48m10.860"],
                ["N32d30m06.503", "W81d49m59.745"],
                ["N32d27m21.822", "W81d49m59.755"],
                ["N32d19m43.966", "W81d43m55.892"],
                ["N32d01m27.257", "W81d59m59.984"],
                ["N31d50m59.392", "W81d59m59.788"],
                ["N31d35m26.863", "W81d47m53.413"],
                ["N31d35m26.382", "W81d28m01.305"],
                ["N31d33m26.671", "W81d26m02.468"],
                ["N31d27m32.555", "W81d26m02.621"]
            ]
        }
    ],
    "fixes": {
        "ANKOR" : ["N31d51m33.995", "W81d12m13.622"],
        "BASLE" : ["N32d09m43.362", "W80d45m48.490"],
        "BROSE" : ["N32d17m12.687", "W81d40m56.549"],
        "CATHY" : ["N31d40m11.624", "W81d10m17.264"],
        "CINBA":  ["N32d17m06.491", "W80d58m40.208"],
        "ESENT":  ["N32d09m28.130", "W80d55m03.779"],
        "FAPLI":  ["N32d15m12.715", "W81d20m58.781"],
        "FILOX":  ["N32d19m42.713", "W81d38m27.873"],
        "FRIES":  ["N32d13m52.696", "W80d47m37.956"],
        "GIPPL":  ["N31d22m53.957", "W81d09m53.696"],
        "HARPS":  ["N31d41m29.560", "W81d15m15.735"],
        "HENIG":  ["N32d10m17.993", "W80d48m13.464"],
        "JANIE":  ["N31d51m33.930", "W81d17m44.602"],
        "JROSS":  ["N32d42m40.008", "W80d37m37.990"],
        "KUCES":  ["N32d42m40.008", "W80d37m37.990"],
        "KSAV":   ["N32d07m39.298", "W81d12m07.675", "Savannah"],
        "LOTTS":  ["N32d20m11.534", "W81d51m17.258"],
        "MAYAR":  ["N32d14m38.620", "W81d32m03.949"],
        "MIZLU":  ["N32d01m04.134", "W81d11m57.267"],
        "MQQ":    ["N31d49m52.344", "W81d30m36.648", "Mc Intosh"],
        "NOMAS":  ["N32d20m54.130", "W80d52m35.932"],
        "PLZZZ":  ["N32d43m50.003", "W81d13m05.983"],
        "REBUS":  ["N32d27m44.115", "W81d00m12.329"],
        "RICKY":  ["N32d04m15.777", "W81d05m38.129"],
        "SAV":    ["N32d08m46.563", "W81d11m56.773", "Savannah"],
        "SINBY":  ["N32d07m38.890", "W81d05m06.814"],
        "SMALZ":  ["N32d28m33.003", "W81d31m40.991"],
        "SOOOP":  ["N32d22m22.996", "W80d33m50.983"],
        "SOVIE":  ["N32d07m47.138", "W81d20m09.427"],
        "SPONG":  ["N32d29m36.132", "W81d23m13.036"],
        "SUTME":  ["N32d20m03.799", "W81d12m05.944"],
        "SVN":    ["N32d00m42.999", "W81d08m27.095", "Hunter"],
        "TELOE":  ["N32d07m34.354", "W80d58m02.690"],
        "TERBE":  ["N31d54m44.803", "W81d11m54.410"],
        "TILEE":  ["N32d07m50.393", "W81d27m14.074"],
        "TILLS":  ["N32d28m44.099", "W81d14m04.844"],
        "TOSEA":  ["N32d14m03.037", "W81d12m03.199"],
        "VIYAP":  ["N31d15m08.147", "W81d26m08.188"],
        "VPBFE":  ["N31d15m08.147", "W81d26m08.188"],
        "VPIWA":  ["N31d48m19.998", "W81d25m50.989"],
        "VPZIE":  ["N32d01m36.996", "W80d53m24.982"],
        "WADEB":  ["N32d07m55.529", "W81d41m22.358"],
        "WISPR":  ["N32d01m58.857", "W81d13m30.705"],
        "WIUMS":  ["N32d10m46.767", "W80d46m05.091"],
        "WOHPY":  ["N31d50m16.922", "W81d12m37.201"],
        "WORIB":  ["N32d02m33.756", "W80d58m07.305"],
        "WOSUG":  ["N31d54m42.722", "W81d17m46.852"],
        "WOXIT":  ["N32d12m51.009", "W81d27m11.107"],
        "YUHVY":  ["N32d11m41.727", "W81d07m18.269"],
        "ZALAV":  ["N32d08m24.287", "W80d49m24.824"],
        "ZUTAN":  ["N31d54m46.609", "W81d06m01.969"]
    },
    "runways":[
        {
            "name": ["10", "28"],
            "end": [
                ["N32d07m43.508", "W81d13m07.690", "10ft"],
                ["N32d07m42.503", "W81d11m18.920", "10ft"]
            ],
            "ils": [true, true]
        }
    ],
    "spawnPatterns": [
        {
            "origin": "KSAV",
            "destination": "",
            "category": "departure",
            "route": "SMALZ",
            "altitude": "",
            "speed": "",
            "method": "random",
            "rate": 15,
            "airlines": [
                ["aal", 3],
                ["aca", 1],
                ["dal", 3],
                ["ual", 3]
            ]
        },
        {
            "origin":"KSAV",
            "destination": "",
            "category": "departure",
            "route": "JROSS",
            "altitude": "",
            "speed": "",
            "method": "random",
            "rate": 15,
            "airlines": [
                ["aal", 3],
                ["aca", 1],
                ["jbu", 3],
                ["ual", 3]
            ]
        },
        {
            "origin": "KSAV",
            "destination": "",
            "category": "departure",
            "route": "GIPPL",
            "altitude": "",
            "speed": "",
            "method": "random",
            "rate": 15,
            "airlines": [
                ["aal", 3],
                ["aca", 1],
                ["dal", 3],
                ["ual", 3]
            ]
        },
        {
            "origin": "",
            "destination": "KSAV",
            "category": "arrival",
            "route": "PLZZZ..SAV",
            "altitude": [10000, 10000],
            "speed": 250,
            "method": "random",
            "rate": 5,
            "airlines": [
                ["aal", 3],
                ["aca", 1],
                ["dal", 3],
                ["ual", 3],
                ["vxp", 1]
            ]
        },
        {
            "origin": "",
            "destination": "KSAV",
            "category": "arrival",
            "route": "VIYAP..SAV",
            "altitude": [10000, 10000],
            "speed": 250,
            "method": "random",
            "rate": 6,
            "airlines": [
                ["aal", 3],
                ["jbu", 3],
                ["dal", 3],
                ["ual", 4],
                ["bwa", 2]
            ]
        },
        {
            "origin": "",
            "destination": "KSAV",
            "category": "arrival",
            "route": "LOTTS..SAV",
            "altitude": [10000, 10000],
            "speed": 250,
            "method": "random",
            "rate": 6,
            "airlines": [
                ["aal", 3],
                ["jbu", 3],
                ["dal", 3],
                ["ual", 4],
                ["nks", 2]
            ]
        }
    ],
        "maps": [
            {
                "name": "Base Map",
                "lines": [
                    ["N31d27m32.536", "W80d47m54.451"],
                ["N31d36m54.489", "W80d40m59.545"],
                ["N31d59m60.000", "W80d28m59.533"],
                ["N32d09m26.793", "W80d38m00.780"],
                ["N32d16m56.773", "W80d40m05.225"],
                ["N32d16m40.446", "W80d49m00.393"],
                ["N32d19m56.757", "W80d55m59.531"],
                ["N32d29m53.114", "W81d01m33.275"],
                ["N32d38m00.659", "W81d01m23.921"],
                ["N32d38m00.473", "W81d27m44.239"],
                ["N32d32m00.423", "W81d33m13.793"],
                ["N32d33m16.359", "W81d41m07.370"],
                ["N32d33m49.489", "W81d43m04.226"],
                ["N32d33m49.487", "W81d45m28.993"],
                ["N32d32m39.052", "W81d48m10.860"],
                ["N32d30m06.503", "W81d49m59.745"],
                ["N32d27m21.822", "W81d49m59.755"],
                ["N32d19m43.966", "W81d43m55.892"],
                ["N32d01m27.257", "W81d59m59.984"],
                ["N31d50m59.392", "W81d59m59.788"],
                ["N31d35m26.863", "W81d47m53.413"],
                ["N31d35m26.382", "W81d28m01.305"],
                ["N31d33m26.671", "W81d26m02.468"],
                ["N31d27m32.555", "W81d26m02.621"]
                ]
            }
        ]
    }
