{
    "icao": "lan",
    "name": "LATAM Airlines Chile",
    "callsign": {
        "name": "Lan Chile",
        "callsignFormats": [
            "###"
        ]
    },
    "fleets": {
        "default": [
            ["A20N", 7],
            ["A319", 18],
            ["A320", 54],
            ["A321", 18],
            ["B763", 16],
            ["B788", 10],
            ["B789", 16]
        ],
        "long": [
            ["B763", 16],
            ["B788", 10],
            ["B789", 16]
        ],
        "short": [
            ["A20N", 7],
            ["A319", 18],
            ["A320", 54],
            ["A321", 18]
        ]
    }
}
